DopplrUtils/__init__.py
DopplrUtils-1.0.1.dist-info/LICENSE.txt
DopplrUtils-1.0.1.dist-info/METADATA
DopplrUtils-1.0.1.dist-info/WHEEL
DopplrUtils-1.0.1.dist-info/top_level.txt
DopplrUtils-1.0.1.dist-info/RECORD
